comibat.py
comibat-0.1.6.dist-info/LICENSE
comibat-0.1.6.dist-info/METADATA
comibat-0.1.6.dist-info/WHEEL
comibat-0.1.6.dist-info/entry_points.txt
comibat-0.1.6.dist-info/top_level.txt
comibat-0.1.6.dist-info/RECORD
