Metadata-Version: 2.1
Name: comibat
Version: 0.1.6
Summary: A tool to add a title page to CBZ comic book archives
Home-page: https://github.com/recoskyler/comibat
Author: Adil Atalay Hamamcioglu
Author-email: 38231748+recoskyler@users.noreply.github.com
License: GNU General Public License v3.0
Classifier: Programming Language :: Python :: 3
Classifier: License :: OSI Approved :: GNU General Public License v3 (GPLv3)
Classifier: Environment :: Console
Classifier: Natural Language :: English
Classifier: Operating System :: POSIX :: Linux
Classifier: Topic :: Utilities
Classifier: Development Status :: 4 - Beta
License-File: LICENSE
Requires-Dist: Click
